{"Basic Information":{"Username":"aceofspayds","Name":"jess","Creation Date":"2012-11-23 01:57:48 UTC","Registration IP":"","Country":""},"Device Information":{"Make":"Apple","Model ID":"iPhone14,2","Model Name":"iPhone 13 Pro","Language":"en","OS Type":"iOS","OS Version":"iOS 17.1.1","Connection Type":"WIFI, CELL"},"Device History":[{"Make":"Apple","Model":"iPhone14,2","Start Time":"2022-07-24 19:00:00 UTC","Device Type":"PHONE"},{"Make":"Apple","Model":"iPhone10,3","Start Time":"2019-11-25 11:00:00 UTC","Device Type":"PHONE"}],"Privacy Policy and Terms of Service Acceptance History":[],"Custom Creative Tools Terms":[],"Login History":[{"IP":"173.59.238.231","Country":"US","Created":"2023-12-07 21:23:15 UTC","Status":"success","Device":"Mozilla/5.0 (iPhone; CPU iPhone OS 17_1_2 like Mac OS X) AppleWebKit/605.1.15 (KHTML, like Gecko) Mobile/15E148"}],"Family Center":[]}